autodiffy/__init__.py
autodiffy/ad_expression.py
autodiffy/binary_tree.py
autodiffy/forward_mode.py
autodiffy/interface.py
autodiffy/optim.py
autodiffy/parse_expression.py
autodiffy/parse_tree.py
autodiffy/reverse_mode.py
autodiffy/terms.py
tests/__init__.py
tests/test_autodiffy.py
tests/test_functions.py
tests/test_optim.py
tests/test_root_solver.py
autodiffy-0.0.2.12.dist-info/LICENSE
autodiffy-0.0.2.12.dist-info/METADATA
autodiffy-0.0.2.12.dist-info/WHEEL
autodiffy-0.0.2.12.dist-info/top_level.txt
autodiffy-0.0.2.12.dist-info/RECORD
